LeetCodeCrawler
