Metadata-Version: 1.2
Name: LeetCodeCrawler
Version: 0.1.5
Summary: A LeetCode Crawler
Home-page: https://github.com/wudizhangzhi/leetcode
Author: wudizhangzhi
Author-email: 554330595@qq.com
License: BSD
Download-URL: https://github.com/wudizhangzhi/leetcode/archive/0.1.5.tar.gz
Keywords: leetcode crawler
Platform: UNKNOWN
Classifier: Development Status :: 3 - Alpha
Classifier: Programming Language :: Python :: 2
Classifier: Programming Language :: Python :: 3
Requires-Python: >=2.6,
